{
  "textbookId": "tango-n4",
  "chapterId": 1,
  "topicId": "topic-1-2",
  "topicName": "会社",
  "topicNameVi": "Công ty",
  "vocabCount": 20,
  "words": [
    {
      "word": "入社",
      "reading": "にゅうしゃ",
      "han_viet": "",
      "meaning": "Vào công ty",
      "type": "Verb",
      "level": "N4",
      "example": {
        "jp": "来月、入社します。",
        "vn": "(đuôi lịch sự)"
      }
    },
    {
      "word": "退社",
      "reading": "たいしゃ",
      "han_viet": "",
      "meaning": "Rời công ty",
      "type": "Verb",
      "level": "N4",
      "example": {
        "jp": "6時に退社しました。",
        "vn": "đã (quá khứ)."
      }
    },
    {
      "word": "転職",
      "reading": "てんしょく",
      "han_viet": "",
      "meaning": "Chuyển việc",
      "type": "Verb",
      "level": "N4",
      "example": {
        "jp": "転職を考えています。",
        "vn": "có (người/động vật)."
      }
    },
    {
      "word": "就職",
      "reading": "しゅうしょく",
      "han_viet": "",
      "meaning": "Tìm việc làm",
      "type": "Verb",
      "level": "N4",
      "example": {
        "jp": "就職活動をしています。",
        "vn": "có (người/động vật)."
      }
    },
    {
      "word": "退職",
      "reading": "たいしょく",
      "han_viet": "",
      "meaning": "Nghỉ việc",
      "type": "Verb",
      "level": "N4",
      "example": {
        "jp": "年末で退職します。",
        "vn": "(đuôi lịch sự)"
      }
    },
    {
      "word": "部署",
      "reading": "ぶしょ",
      "han_viet": "",
      "meaning": "Bộ phận",
      "type": "Noun",
      "level": "N4",
      "example": {
        "jp": "新しい部署に移動しました。",
        "vn": "đã (quá khứ)."
      }
    },
    {
      "word": "上司",
      "reading": "じょうし",
      "han_viet": "",
      "meaning": "Cấp trên",
      "type": "Noun",
      "level": "N4",
      "example": {
        "jp": "上司に相談しました。",
        "vn": "đã (quá khứ)."
      }
    },
    {
      "word": "部下",
      "reading": "ぶか",
      "han_viet": "",
      "meaning": "Cấp dưới",
      "type": "Noun",
      "level": "N4",
      "example": {
        "jp": "部下を指導しています。",
        "vn": "có (người/động vật)."
      }
    },
    {
      "word": "同僚",
      "reading": "どうりょう",
      "han_viet": "",
      "meaning": "Đồng nghiệp",
      "type": "Noun",
      "level": "N4",
      "example": {
        "jp": "同僚と食事に行きました。",
        "vn": "đã (quá khứ)."
      }
    },
    {
      "word": "取引先",
      "reading": "とりひきさき",
      "han_viet": "",
      "meaning": "Đối tác",
      "type": "Noun",
      "level": "N4",
      "example": {
        "jp": "取引先と会議しました。",
        "vn": "đã (quá khứ)."
      }
    },
    {
      "word": "人事",
      "reading": "じんじ",
      "han_viet": "",
      "meaning": "Nhân sự",
      "type": "Noun",
      "level": "N4",
      "example": {
        "jp": "人事部に届け出ました。",
        "vn": "đã (quá khứ)."
      }
    },
    {
      "word": "総務",
      "reading": "そうむ",
      "han_viet": "",
      "meaning": "Tổng vụ",
      "type": "Noun",
      "level": "N4",
      "example": {
        "jp": "総務部で働いています。",
        "vn": "có (người/động vật)."
      }
    },
    {
      "word": "経理",
      "reading": "けいり",
      "han_viet": "",
      "meaning": "Kế toán",
      "type": "Noun",
      "level": "N4",
      "example": {
        "jp": "経理部に所属しています。",
        "vn": "có (người/động vật)."
      }
    },
    {
      "word": "営業",
      "reading": "えいぎょう",
      "han_viet": "",
      "meaning": "Kinh doanh",
      "type": "Noun",
      "level": "N4",
      "example": {
        "jp": "営業部で働いています。",
        "vn": "có (người/động vật)."
      }
    },
    {
      "word": "開発",
      "reading": "かいはつ",
      "han_viet": "",
      "meaning": "Phát triển",
      "type": "Verb",
      "level": "N4",
      "example": {
        "jp": "新商品を開発しています。",
        "vn": "có (người/động vật)."
      }
    },
    {
      "word": "製造",
      "reading": "せいぞう",
      "han_viet": "",
      "meaning": "Sản xuất",
      "type": "Verb",
      "level": "N4",
      "example": {
        "jp": "工場で製造しています。",
        "vn": "có (người/động vật)."
      }
    },
    {
      "word": "販売",
      "reading": "はんばい",
      "han_viet": "",
      "meaning": "Bán hàng",
      "type": "Verb",
      "level": "N4",
      "example": {
        "jp": "全国で販売しています。",
        "vn": "có (người/động vật)."
      }
    },
    {
      "word": "輸入",
      "reading": "ゆにゅう",
      "han_viet": "",
      "meaning": "Nhập khẩu",
      "type": "Verb",
      "level": "N4",
      "example": {
        "jp": "海外から輸入しています。",
        "vn": "có (người/động vật)."
      }
    },
    {
      "word": "輸出",
      "reading": "ゆしゅつ",
      "han_viet": "",
      "meaning": "Xuất khẩu",
      "type": "Verb",
      "level": "N4",
      "example": {
        "jp": "世界各国に輸出しています。",
        "vn": "có (người/động vật)."
      }
    },
    {
      "word": "売上",
      "reading": "うりあげ",
      "han_viet": "",
      "meaning": "Doanh thu",
      "type": "Noun",
      "level": "N4",
      "example": {
        "jp": "売上が伸びました。",
        "vn": "đã (quá khứ)."
      }
    }
  ]
}
